ate/__init__.py
ate/bridge_server.py
ate/cli.py
ate/compatibility.py
ate/generator.py
ate/marketplace.py
ate/mcp_server.py
ate/primitives.py
ate/robot_setup.py
ate/skill_schema.py
ate/behaviors/__init__.py
ate/behaviors/common.py
ate/behaviors/tree.py
ate/drivers/__init__.py
ate/drivers/mechdog.py
ate/generators/__init__.py
ate/generators/docker_generator.py
ate/generators/hardware_config.py
ate/generators/ros2_generator.py
ate/generators/skill_generator.py
ate/interfaces/__init__.py
ate/interfaces/base.py
ate/interfaces/body.py
ate/interfaces/detection.py
ate/interfaces/locomotion.py
ate/interfaces/manipulation.py
ate/interfaces/navigation.py
ate/interfaces/perception.py
ate/interfaces/types.py
ate/recording/__init__.py
ate/recording/demonstration.py
ate/recording/session.py
ate/recording/upload.py
ate/recording/wrapper.py
ate/robot/__init__.py
ate/robot/calibration.py
ate/robot/commands.py
ate/robot/discovery.py
ate/robot/introspection.py
ate/robot/manager.py
ate/robot/profiles.py
ate/robot/registry.py
ate/robot/skill_upload.py
ate/robot/visual_labeler.py
ate/telemetry/__init__.py
ate/telemetry/cli.py
ate/telemetry/collector.py
ate/telemetry/context.py
ate/telemetry/fleet_agent.py
ate/telemetry/types.py
ate/telemetry/formats/__init__.py
ate/telemetry/formats/hdf5_serializer.py
ate/telemetry/formats/mcap_serializer.py
mechdog_labeled/__init__.py
mechdog_labeled/primitives.py
mechdog_labeled/servo_map.py
mechdog_output/__init__.py
mechdog_output/primitives.py
mechdog_output/servo_map.py
test_autodetect/__init__.py
test_autodetect/primitives.py
test_autodetect/servo_map.py
test_full_auto/__init__.py
test_full_auto/primitives.py
test_full_auto/servo_map.py
test_smart_detect/__init__.py
test_smart_detect/primitives.py
test_smart_detect/servo_map.py
foodforthought_cli-0.2.8.dist-info/METADATA
foodforthought_cli-0.2.8.dist-info/WHEEL
foodforthought_cli-0.2.8.dist-info/entry_points.txt
foodforthought_cli-0.2.8.dist-info/top_level.txt
foodforthought_cli-0.2.8.dist-info/RECORD
