Metadata-Version: 2.4
Name: foodforthought-cli
Version: 0.2.8
Summary: CLI tool for FoodforThought robotics repository platform - manage robot skills and data
Home-page: https://kindly.fyi/foodforthought
Author: Kindly Robotics
Author-email: hello@kindly.fyi
Project-URL: Homepage, https://kindly.fyi
Project-URL: Documentation, https://kindly.fyi/foodforthought/cli
Project-URL: Source, https://github.com/kindlyrobotics/monorepo
Project-URL: Bug Tracker, https://github.com/kindlyrobotics/monorepo/issues
Keywords: robotics,robot-skills,machine-learning,data-management,cli
Classifier: Development Status :: 3 - Alpha
Classifier: Intended Audience :: Developers
Classifier: Intended Audience :: Science/Research
Classifier: Topic :: Software Development :: Version Control
Classifier: Topic :: Scientific/Engineering :: Artificial Intelligence
Classifier: License :: OSI Approved :: MIT License
Classifier: Programming Language :: Python :: 3
Classifier: Programming Language :: Python :: 3.8
Classifier: Programming Language :: Python :: 3.9
Classifier: Programming Language :: Python :: 3.10
Classifier: Programming Language :: Python :: 3.11
Classifier: Programming Language :: Python :: 3.12
Requires-Python: >=3.8
Requires-Dist: requests>=2.28.0
Provides-Extra: robot-setup
Requires-Dist: pyserial>=3.5; extra == "robot-setup"
Requires-Dist: anthropic>=0.18.0; extra == "robot-setup"
Provides-Extra: detection
Requires-Dist: Pillow>=9.0.0; extra == "detection"
Provides-Extra: visual-labeling
Requires-Dist: pyserial>=3.5; extra == "visual-labeling"
Requires-Dist: opencv-python>=4.5.0; extra == "visual-labeling"
Requires-Dist: Pillow>=9.0.0; extra == "visual-labeling"
Provides-Extra: all
Requires-Dist: pyserial>=3.5; extra == "all"
Requires-Dist: anthropic>=0.18.0; extra == "all"
Requires-Dist: Pillow>=9.0.0; extra == "all"
Requires-Dist: opencv-python>=4.5.0; extra == "all"
Dynamic: author
Dynamic: author-email
Dynamic: classifier
Dynamic: description
Dynamic: description-content-type
Dynamic: home-page
Dynamic: keywords
Dynamic: project-url
Dynamic: provides-extra
Dynamic: requires-dist
Dynamic: requires-python
Dynamic: summary
